sanpy/__init__.py
sanpy/_util.py
sanpy/_version.py
sanpy/analysisDir.py
sanpy/analysisPlot.py
sanpy/analysisUtil.py
sanpy/atfStim.py
sanpy/bAbfText.py
sanpy/bAnalysisResults.py
sanpy/bAnalysisStim.py
sanpy/bAnalysisUtil.py
sanpy/bAnalysis_.py
sanpy/bDetection.py
sanpy/bExport.py
sanpy/detectionUtils.py
sanpy/epochAnalysis.py
sanpy/fftUtils.py
sanpy/h5Util.py
sanpy/kymAnalysis.py
sanpy/metaData.py
sanpy/readme.md
sanpy/sanpyLogger.py
sanpy/vClampAnalysis.py
sanpy/version.py
sanpy/_userFiles/SanPy-User-Files/analysis/exampleUserAnalysis.py
sanpy/_userFiles/SanPy-User-Files/detection/.placeholder
sanpy/_userFiles/SanPy-User-Files/exampleData/19114000.abf
sanpy/_userFiles/SanPy-User-Files/exampleData/19114001.abf
sanpy/_userFiles/SanPy-User-Files/exampleData/20191009_0005.abf
sanpy/_userFiles/SanPy-User-Files/exampleData/2021_07_20_0010.abf
sanpy/_userFiles/SanPy-User-Files/exampleData/2021_07_20_0010.sanpy
sanpy/_userFiles/SanPy-User-Files/file loaders/.placeholder
sanpy/_userFiles/SanPy-User-Files/plugins/exampleUserPlugin1.py
sanpy/_userFiles/SanPy-User-Files/preferences/.placeholder
sanpy/detection-presets/Ca Kymograph.json
sanpy/detection-presets/Ca Spikes.json
sanpy/detection-presets/Default.json
sanpy/detection-presets/Fast Neuron.json
sanpy/detection-presets/Neuron.json
sanpy/detection-presets/SA Node.json
sanpy/detection-presets/Sub Threshold.json
sanpy/detection-presets/Ventricular.json
sanpy/detection-presets/Wu-iPSC.json
sanpy/fileloaders/__init__.py
sanpy/fileloaders/epochTable.py
sanpy/fileloaders/fileLoader_abf.py
sanpy/fileloaders/fileLoader_atf.py
sanpy/fileloaders/fileLoader_base.py
sanpy/fileloaders/fileLoader_csv.py
sanpy/fileloaders/fileLoader_tif.py
sanpy/interface/__init__.py
sanpy/interface/bDetectionWidget.py
sanpy/interface/bDialog.py
sanpy/interface/bErrorTable.py
sanpy/interface/bExportWidget.py
sanpy/interface/bFileTable.py
sanpy/interface/bKymographWidget.py
sanpy/interface/bPlugins.py
sanpy/interface/bScatterPlotWidget2.py
sanpy_ephys-0.2.3.post13.dist-info/LICENSE
sanpy_ephys-0.2.3.post13.dist-info/METADATA
sanpy_ephys-0.2.3.post13.dist-info/WHEEL
sanpy_ephys-0.2.3.post13.dist-info/entry_points.txt
sanpy_ephys-0.2.3.post13.dist-info/top_level.txt
sanpy_ephys-0.2.3.post13.dist-info/RECORD
