Metadata-Version: 2.1
Name: sanpy-ephys
Version: 0.2.3.post13
Summary: Whole cell current-clamp analysis.
Home-page: http://github.com/cudmore/SanPy
Author: Robert H Cudmore
Author-email: rhcudmore@ucdavis.edu
License: GNU General Public License, Version 3
Classifier: Programming Language :: Python :: 3
Classifier: Natural Language :: English
Classifier: License :: OSI Approved :: GNU General Public License v3 (GPLv3)
Classifier: Operating System :: MacOS
Classifier: Operating System :: Microsoft :: Windows
Classifier: Intended Audience :: Developers
Classifier: Intended Audience :: Science/Research
Classifier: Intended Audience :: End Users/Desktop
Classifier: Topic :: Scientific/Engineering :: Bio-Informatics
Classifier: Topic :: Scientific/Engineering :: Information Analysis
Classifier: Topic :: Scientific/Engineering :: Medical Science Apps.
Classifier: Topic :: Scientific/Engineering :: Visualization
Classifier: Topic :: Software Development :: Libraries :: Python Modules
Classifier: Topic :: Software Development :: Libraries :: Application Frameworks
Requires-Python: >=3.8
License-File: LICENSE
Provides-Extra: dev
Requires-Dist: numpy ; extra == 'dev'
Requires-Dist: pandas ; extra == 'dev'
Requires-Dist: scipy ; extra == 'dev'
Requires-Dist: pyabf ; extra == 'dev'
Requires-Dist: tifffile ; extra == 'dev'
Requires-Dist: matplotlib ; extra == 'dev'
Requires-Dist: mplcursors ; extra == 'dev'
Requires-Dist: seaborn ; extra == 'dev'
Requires-Dist: requests ; extra == 'dev'
Requires-Dist: tables ; extra == 'dev'
Requires-Dist: scikit-image ; extra == 'dev'
Requires-Dist: h5py ; extra == 'dev'
Requires-Dist: qtpy ; extra == 'dev'
Requires-Dist: pyqtgraph ; extra == 'dev'
Requires-Dist: pyqtdarktheme ; extra == 'dev'
Requires-Dist: PyQt5 ; extra == 'dev'
Requires-Dist: mkdocs ; extra == 'dev'
Requires-Dist: mkdocs-material ; extra == 'dev'
Requires-Dist: mkdocs-jupyter ; extra == 'dev'
Requires-Dist: mkdocstrings ; extra == 'dev'
Requires-Dist: mkdocstrings-python ; extra == 'dev'
Requires-Dist: tornado ; extra == 'dev'
Requires-Dist: pyinstaller ; extra == 'dev'
Requires-Dist: ipython ; extra == 'dev'
Requires-Dist: jupyter ; extra == 'dev'
Requires-Dist: tox ; extra == 'dev'
Requires-Dist: pytest ; extra == 'dev'
Requires-Dist: pytest-cov ; extra == 'dev'
Requires-Dist: pytest-qt ; extra == 'dev'
Requires-Dist: flake8 ; extra == 'dev'
Provides-Extra: gui
Requires-Dist: numpy ; extra == 'gui'
Requires-Dist: pandas ; extra == 'gui'
Requires-Dist: scipy ; extra == 'gui'
Requires-Dist: pyabf ; extra == 'gui'
Requires-Dist: tifffile ; extra == 'gui'
Requires-Dist: matplotlib ; extra == 'gui'
Requires-Dist: mplcursors ; extra == 'gui'
Requires-Dist: seaborn ; extra == 'gui'
Requires-Dist: requests ; extra == 'gui'
Requires-Dist: tables ; extra == 'gui'
Requires-Dist: scikit-image ; extra == 'gui'
Requires-Dist: h5py ; extra == 'gui'
Requires-Dist: qtpy ; extra == 'gui'
Requires-Dist: pyqtgraph ; extra == 'gui'
Requires-Dist: pyqtdarktheme ; extra == 'gui'
Requires-Dist: PyQt5 ; extra == 'gui'
Provides-Extra: test
Requires-Dist: numpy ; extra == 'test'
Requires-Dist: pandas ; extra == 'test'
Requires-Dist: scipy ; extra == 'test'
Requires-Dist: pyabf ; extra == 'test'
Requires-Dist: tifffile ; extra == 'test'
Requires-Dist: matplotlib ; extra == 'test'
Requires-Dist: mplcursors ; extra == 'test'
Requires-Dist: seaborn ; extra == 'test'
Requires-Dist: requests ; extra == 'test'
Requires-Dist: tables ; extra == 'test'
Requires-Dist: scikit-image ; extra == 'test'
Requires-Dist: h5py ; extra == 'test'
Requires-Dist: qtpy ; extra == 'test'
Requires-Dist: pyqtgraph ; extra == 'test'
Requires-Dist: pyqtdarktheme ; extra == 'test'
Requires-Dist: PyQt5 ; extra == 'test'
Requires-Dist: tox ; extra == 'test'
Requires-Dist: pytest ; extra == 'test'
Requires-Dist: pytest-cov ; extra == 'test'
Requires-Dist: pytest-qt ; extra == 'test'
Requires-Dist: flake8 ; extra == 'test'
